verilog/rtl/test_bench.v
`timescale 1ns / 1ps

module cyclic_flag_tb;

    reg CLK;
    reg RST;
    wire [11:0] shift_reg;

    // Instantiate the cyclic_flag module
    cyclic_flag uut (
        .CLK(CLK),
        .RST(RST),
        .shift_reg(shift_reg)
    );

    // Clock generation: 50 MHz clock with a period of 20ns
    initial begin
        CLK = 0;
        forever #10 CLK = ~CLK; // Toggle clock every 10ns
    end

    // Test sequence
    initial begin
        // Initialize inputs
        RST = 1;
        #25;
        RST = 0;
        #500; // Run simulation for 500ns
        $finish;
    end

    // Monitor outputs
    initial begin
        $monitor("Time=%0t ns | RST=%b | shift_reg=%b", $time, RST, shift_reg);
    end

    // Dump waveforms for GTKWave
    initial begin
        $dumpfile("cyclic_flag_tb.vcd"); // Name of the dump file
        $dumpvars(0, cyclic_flag_tb);    // Dump all variables in this module
    end

endmodule

module cyclic_flag (
    input CLK,
    input RST,
    output reg [0:11] shift_reg
);

    always @(posedge CLK) begin
        if (RST) begin
            // Initialize the shift register with '1' at the least significant bit
            shift_reg <= 12'b000000000000;
        end else if (shift_reg[0] == 1'b0) begin
            // Shift left by one position and set LSB to '1' to accumulate ones
            shift_reg <= (shift_reg << 1) | 1'b1;
        end else begin
            // Hold the value when all bits are '1'
            shift_reg <= shift_reg;
        end
    end

endmodule

verilog/rtl/cyclic_flag_tb.vcd
$date
	Thu Oct 10 04:15:53 2024
$end
$version
	Icarus Verilog
$end
$timescale
	1ps
$end
$scope module cyclic_flag_tb $end
$var wire 12 ! shift_reg [11:0] $end
$var reg 1 " CLK $end
$var reg 1 # RST $end
$scope module uut $end
$var wire 1 " CLK $end
$var wire 1 # RST $end
$var reg 12 $ shift_reg [0:11] $end
$upscope $end
$upscope $end
$enddefinitions $end
#0
$dumpvars
bx $
1#
0"
bx !
$end
#10000
b0 !
b0 $
1"
#20000
0"
#25000
0#
#30000
b1 !
b1 $
1"
#40000
0"
#50000
b11 !
b11 $
1"
#60000
0"
#70000
b111 !
b111 $
1"
#80000
0"
#90000
b1111 !
b1111 $
1"
#100000
0"
#110000
b11111 !
b11111 $
1"
#120000
0"
#130000
b111111 !
b111111 $
1"
#140000
0"
#150000
b1111111 !
b1111111 $
1"
#160000
0"
#170000
b11111111 !
b11111111 $
1"
#180000
0"
#190000
b111111111 !
b111111111 $
1"
#200000
0"
#210000
b1111111111 !
b1111111111 $
1"
#220000
0"
#230000
b11111111111 !
b11111111111 $
1"
#240000
0"
#250000
b111111111111 !
b111111111111 $
1"
