verilog/rtl/sar_controller.v
module sar_controller (
    input        RST,
    input        CLK,
    input        COMP_P,
    input        COMP_N,
    output       CLKS,
    output       CLKSB,
    output       EOC,
    output [0:9] CF,
    output [0:9] DOUT,
    output [0:9] CDAC_P,
    output [0:9] CDAC_N
  );

  // Instantiate auto_sampling module
  auto_sampling auto_samp_inst (
                  .RST  (RST),
                  .CLK_S (CLK),
                  .CLKS  (CLKS),
                  .CLKSB (CLKSB)
                );

  // Instantiate cyclic_flag module
  cyclic_flag cyclic_flag_inst (
                .CLK (CLK),
                .RST (CLKSB),
                .CF  (CF),
                .EOC (EOC)
              );

  // Instantiate cdac_controller module
  cdac_controller cdac_ctrl_inst (
                    .CH     (CF),
                    .CLK_NS (CLK),
                    .COMP_P (COMP_P),
                    .COMP_N (COMP_N),
                    .CLKS   (CLKS),
                    .CDAC_P (CDAC_P),
                    .CDAC_N (CDAC_N)
                  );

  // Instantiate data_latch module
  data_latch data_latch_inst (
               .EOC     (EOC),
               .DATA_IN (CDAC_P),
               .DOUT    (DOUT)
             );

endmodule

module auto_sampling (
    input RST,
    input  CLK_S,
    output reg CLKS,
    output reg CLKSB
  );

  reg [3:0] COUNTER;

  always @(posedge CLK_S)
  begin
    if(RST)
    begin
      COUNTER <= 4'b0000;
      CLKS    <= 0;
      CLKSB   <= 1;
    end
    else
    begin
      if (COUNTER < 4'b1111)
      begin
        COUNTER <= COUNTER + 1;
      end
      else
      begin
        COUNTER <= 4'b0000;
        CLKS    <= ~CLKS;
        CLKSB   <= ~CLKSB;
      end
    end
  end

endmodule

module cdac_controller (
    input      [0:9] CH,
    input             CLK_NS,
    input             COMP_P,
    input             COMP_N,
    input             CLKS,
    output reg [0:9] CDAC_P,
    output reg [0:9] CDAC_N
  );
  
  reg [3:0] COUNTER; // 4-bit counter untuk menghitung dari 0 hingga 10

  always @(negedge CLK_NS or negedge CLKS)
  begin
    if (!CLKS) // Reset ketika CLKS rendah
    begin
      COUNTER <= 4'd10;
      CDAC_P  <= 10'b0;
      CDAC_N  <= 10'b0;
    end
    else
    begin
      if (COUNTER > 0)
      begin
        COUNTER <= COUNTER - 1;
        if (COUNTER <= 10)
        begin
          CDAC_P[COUNTER] <= COMP_P & CH[COUNTER];
          CDAC_N[COUNTER] <= COMP_N & CH[COUNTER];
        end
      end
    end
  end

endmodule


module data_latch (
    input        EOC,
    input  [0:9] DATA_IN,
    output reg [0:9] DOUT
  );

  always @(posedge EOC)
  begin
    DOUT <= DATA_IN;
  end

endmodule

module cyclic_flag (
    input  CLK,
    input  RST,
    output reg [0:9] CF,
    output reg EOC
  );

  always @(posedge CLK)
  begin
    if (RST)
    begin
      CF <= 10'b0;
    end
    else if (CF[0] == 1'b0)
    begin
      CF <= {CF[1:9], 1'b1}; // Shift left and set LSB to '1'
    end
    else
    begin
      CF <= CF;
    end
    EOC <= CF[0];
  end

endmodule

verilog/rtl/test_bench.v
`timescale 1ns / 1ps

module sar_controller_tb;

  // Sinyal Testbench
  reg        RST;
  reg        CLK;
  reg        COMP_P;
  reg        COMP_N;
  wire       CLKS;
  wire       CLKSB;
  wire       EOC;
  wire [0:9] CF;
  wire [0:9] DOUT;
  wire [0:9] CDAC_P;
  wire [0:9] CDAC_N;

  // Instansiasi SAR controller
  sar_controller uut (
                   .RST (RST),
                   .CLK    (CLK),
                   .COMP_P (COMP_P),
                   .COMP_N (COMP_N),
                   .CLKS   (CLKS),
                   .CLKSB  (CLKSB),
                   .EOC    (EOC),
                   .CF     (CF),
                   .DOUT   (DOUT),
                   .CDAC_P (CDAC_P),
                   .CDAC_N (CDAC_N)
                 );

  // Pembuatan sinyal clock
  initial
  begin
    CLK = 0;
    forever
      #5 CLK = ~CLK; // Periode clock 10ns (100 MHz)
  end

  // Sinyal RST
  initial
  begin
    RST = 1;
    #15 RST = 0; // Aktifkan setelah 15ns
  end

  // Simulasi input komparator
  initial
  begin
    COMP_P = 0;
    COMP_N = 0;
    // Tunggu hingga sistem diaktifkan
    wait (RST == 0);
    #10; // Delay kecil setelah diaktifkan

    // Simulasikan output komparator untuk konversi 10-bit
    repeat (1000)
    begin
      @(negedge CLK);
      // Berikan nilai uji ke COMP_P dan COMP_N
      // Sebagai contoh, kita gunakan nilai acak 0 dan 1
      COMP_P = $random % 2;
      COMP_N = ~COMP_P;
    end
  end

  // Dump waveform ke file
  initial
  begin
    $dumpfile("sar_controller_tb.vcd"); // Nama file waveform
    $dumpvars(0, sar_controller_tb);    // Dump semua variabel dalam modul ini
  end

  // Mengakhiri simulasi
  initial
  begin
    #2000;
    $finish;
  end

endmodule

verilog/rtl/sar_controller_tb.vcd
$date
	Wed Nov 20 03:33:57 2024
$end
$version
	Icarus Verilog
$end
$timescale
	1ps
$end
$scope module sar_controller_tb $end
$var wire 1 ! EOC $end
$var wire 10 " DOUT [0:9] $end
$var wire 1 # CLKSB $end
$var wire 1 $ CLKS $end
$var wire 10 % CF [0:9] $end
$var wire 10 & CDAC_P [0:9] $end
$var wire 10 ' CDAC_N [0:9] $end
$var reg 1 ( CLK $end
$var reg 1 ) COMP_N $end
$var reg 1 * COMP_P $end
$var reg 1 + RST $end
$scope module uut $end
$var wire 1 ( CLK $end
$var wire 1 ) COMP_N $end
$var wire 1 * COMP_P $end
$var wire 1 + RST $end
$var wire 1 ! EOC $end
$var wire 10 , DOUT [0:9] $end
$var wire 1 # CLKSB $end
$var wire 1 $ CLKS $end
$var wire 10 - CF [0:9] $end
$var wire 10 . CDAC_P [0:9] $end
$var wire 10 / CDAC_N [0:9] $end
$scope module auto_samp_inst $end
$var wire 1 ( CLK_S $end
$var wire 1 + RST $end
$var reg 1 $ CLKS $end
$var reg 1 # CLKSB $end
$var reg 4 0 COUNTER [3:0] $end
$upscope $end
$scope module cdac_ctrl_inst $end
$var wire 1 $ CLKS $end
$var wire 1 ( CLK_NS $end
$var wire 1 ) COMP_N $end
$var wire 1 * COMP_P $end
$var wire 10 1 CH [0:9] $end
$var reg 10 2 CDAC_N [0:9] $end
$var reg 10 3 CDAC_P [0:9] $end
$var reg 4 4 COUNTER [3:0] $end
$upscope $end
$scope module cyclic_flag_inst $end
$var wire 1 ( CLK $end
$var wire 1 # RST $end
$var reg 10 5 CF [0:9] $end
$var reg 1 ! EOC $end
$upscope $end
$scope module data_latch_inst $end
$var wire 10 6 DATA_IN [0:9] $end
$var wire 1 ! EOC $end
$var reg 10 7 DOUT [0:9] $end
$upscope $end
$upscope $end
$upscope $end
$enddefinitions $end
#0
$dumpvars
bx 7
bx 6
bx 5
bx 4
bx 3
bx 2
bx 1
bx 0
bx /
bx .
bx -
bx ,
1+
0*
0)
0(
bx '
bx &
bx %
x$
x#
bx "
x!
$end
#5000
b0 %
b0 -
b0 1
b0 5
b0 '
b0 /
b0 2
b0 &
b0 .
b0 3
b0 6
b1010 4
1#
0$
b0 0
1(
#10000
0(
#15000
b1 0
0!
1(
0+
#20000
0(
#25000
b10 0
1(
#30000
1)
0(
#35000
b11 0
1(
#40000
0)
1*
0(
#45000
b100 0
1(
#50000
0(
#55000
b101 0
1(
#60000
0(
#65000
b110 0
1(
#70000
0(
#75000
b111 0
1(
#80000
0(
#85000
b1000 0
1(
#90000
0(
#95000
b1001 0
1(
#100000
1)
0*
0(
#105000
b1010 0
1(
#110000
0)
1*
0(
#115000
b1011 0
1(
#120000
0(
#125000
b1100 0
1(
#130000
1)
0*
0(
#135000
b1101 0
1(
#140000
0)
1*
0(
#145000
b1110 0
1(
#150000
0(
#155000
b1111 0
1(
#160000
1)
0*
0(
#165000
0#
1$
b0 0
1(
#170000
b1001 4
0)
1*
0(
#175000
b1 0
b1 %
b1 -
b1 1
b1 5
1(
#180000
b1 '
b1 /
b1 2
b1000 4
1)
0*
0(
#185000
b10 0
b11 %
b11 -
b11 1
b11 5
1(
#190000
b10 &
b10 .
b10 3
b10 6
b111 4
0)
1*
0(
#195000
b11 0
b111 %
b111 -
b111 1
b111 5
1(
#200000
b101 '
b101 /
b101 2
b110 4
1)
0*
0(
#205000
b100 0
b1111 %
b1111 -
b1111 1
b1111 5
1(
#210000
b1010 &
b1010 .
b1010 3
b1010 6
b101 4
0)
1*
0(
#215000
b101 0
b11111 %
b11111 -
b11111 1
b11111 5
1(
#220000
b11010 &
b11010 .
b11010 3
b11010 6
b100 4
0(
#225000
b110 0
b111111 %
b111111 -
b111111 1
b111111 5
1(
#230000
b100101 '
b100101 /
b100101 2
b11 4
1)
0*
0(
#235000
b111 0
b1111111 %
b1111111 -
b1111111 1
b1111111 5
1(
#240000
b1011010 &
b1011010 .
b1011010 3
b1011010 6
b10 4
0)
1*
0(
#245000
b1000 0
b11111111 %
b11111111 -
b11111111 1
b11111111 5
1(
#250000
b10100101 '
b10100101 /
b10100101 2
b1 4
1)
0*
0(
#255000
b1001 0
b111111111 %
b111111111 -
b111111111 1
b111111111 5
1(
#260000
b110100101 '
b110100101 /
b110100101 2
b0 4
0(
#265000
b1010 0
b1111111111 %
b1111111111 -
b1111111111 1
b1111111111 5
1(
#270000
0(
#275000
b1011010 "
b1011010 ,
b1011010 7
b1011 0
1!
1(
#280000
0)
1*
0(
#285000
b1100 0
1(
#290000
1)
0*
0(
#295000
b1101 0
1(
#300000
0)
1*
0(
#305000
b1110 0
1(
#310000
0(
#315000
b1111 0
1(
#320000
0(
#325000
b0 %
b0 -
b0 1
b0 5
b0 '
b0 /
b0 2
b0 &
b0 .
b0 3
b0 6
b1010 4
1#
0$
b0 0
1(
#330000
0(
#335000
b1 0
0!
1(
#340000
1)
0*
0(
#345000
b10 0
1(
#350000
0(
#355000
b11 0
1(
#360000
0(
#365000
b100 0
1(
#370000
0(
#375000
b101 0
1(
#380000
0)
1*
0(
#385000
b110 0
1(
#390000
1)
0*
0(
#395000
b111 0
1(
#400000
0)
1*
0(
#405000
b1000 0
1(
#410000
0(
#415000
b1001 0
1(
#420000
0(
#425000
b1010 0
1(
#430000
0(
#435000
b1011 0
1(
#440000
0(
#445000
b1100 0
1(
#450000
1)
0*
0(
#455000
b1101 0
1(
#460000
0(
#465000
b1110 0
1(
#470000
0)
1*
0(
#475000
b1111 0
1(
#480000
0(
#485000
0#
1$
b0 0
1(
#490000
b1001 4
0(
#495000
b1 0
b1 %
b1 -
b1 1
b1 5
1(
#500000
b1 '
b1 /
b1 2
b1000 4
1)
0*
0(
#505000
b10 0
b11 %
b11 -
b11 1
b11 5
1(
#510000
b11 '
b11 /
b11 2
b111 4
0(
#515000
b11 0
b111 %
b111 -
b111 1
b111 5
1(
#520000
b111 '
b111 /
b111 2
b110 4
0(
#525000
b100 0
b1111 %
b1111 -
b1111 1
b1111 5
1(
#530000
b1111 '
b1111 /
b1111 2
b101 4
0(
#535000
b101 0
b11111 %
b11111 -
b11111 1
b11111 5
1(
#540000
b11111 '
b11111 /
b11111 2
b100 4
0(
#545000
b110 0
b111111 %
b111111 -
b111111 1
b111111 5
1(
#550000
b100000 &
b100000 .
b100000 3
b100000 6
b11 4
0)
1*
0(
#555000
b111 0
b1111111 %
b1111111 -
b1111111 1
b1111111 5
1(
#560000
b1011111 '
b1011111 /
b1011111 2
b10 4
1)
0*
0(
#565000
b1000 0
b11111111 %
b11111111 -
b11111111 1
b11111111 5
1(
#570000
b11011111 '
b11011111 /
b11011111 2
b1 4
0(
#575000
b1001 0
b111111111 %
b111111111 -
b111111111 1
b111111111 5
1(
#580000
b100100000 &
b100100000 .
b100100000 3
b100100000 6
b0 4
0)
1*
0(
#585000
b1010 0
b1111111111 %
b1111111111 -
b1111111111 1
b1111111111 5
1(
#590000
0(
#595000
b100100000 "
b100100000 ,
b100100000 7
b1011 0
1!
1(
#600000
1)
0*
0(
#605000
b1100 0
1(
#610000
0(
#615000
b1101 0
1(
#620000
0(
#625000
b1110 0
1(
#630000
0(
#635000
b1111 0
1(
#640000
0(
#645000
b0 %
b0 -
b0 1
b0 5
b0 '
b0 /
b0 2
b0 &
b0 .
b0 3
b0 6
b1010 4
1#
0$
b0 0
1(
#650000
0)
1*
0(
#655000
b1 0
0!
1(
#660000
0(
#665000
b10 0
1(
#670000
0(
#675000
b11 0
1(
#680000
0(
#685000
b100 0
1(
#690000
0(
#695000
b101 0
1(
#700000
1)
0*
0(
#705000
b110 0
1(
#710000
0(
#715000
b111 0
1(
#720000
0)
1*
0(
#725000
b1000 0
1(
#730000
0(
#735000
b1001 0
1(
#740000
0(
#745000
b1010 0
1(
#750000
1)
0*
0(
#755000
b1011 0
1(
#760000
0(
#765000
b1100 0
1(
#770000
0)
1*
0(
#775000
b1101 0
1(
#780000
0(
#785000
b1110 0
1(
#790000
1)
0*
0(
#795000
b1111 0
1(
#800000
0)
1*
0(
#805000
0#
1$
b0 0
1(
#810000
b1001 4
0(
#815000
b1 0
b1 %
b1 -
b1 1
b1 5
1(
#820000
b1 '
b1 /
b1 2
b1000 4
1)
0*
0(
#825000
b10 0
b11 %
b11 -
b11 1
b11 5
1(
#830000
b10 &
b10 .
b10 3
b10 6
b111 4
0)
1*
0(
#835000
b11 0
b111 %
b111 -
b111 1
b111 5
1(
#840000
b110 &
b110 .
b110 3
b110 6
b110 4
0(
#845000
b100 0
b1111 %
b1111 -
b1111 1
b1111 5
1(
#850000
b1110 &
b1110 .
b1110 3
b1110 6
b101 4
0(
#855000
b101 0
b11111 %
b11111 -
b11111 1
b11111 5
1(
#860000
b10001 '
b10001 /
b10001 2
b100 4
1)
0*
0(
#865000
b110 0
b111111 %
b111111 -
b111111 1
b111111 5
1(
#870000
b101110 &
b101110 .
b101110 3
b101110 6
b11 4
0)
1*
0(
#875000
b111 0
b1111111 %
b1111111 -
b1111111 1
b1111111 5
1(
#880000
b1101110 &
b1101110 .
b1101110 3
b1101110 6
b10 4
0(
#885000
b1000 0
b11111111 %
b11111111 -
b11111111 1
b11111111 5
1(
#890000
b10010001 '
b10010001 /
b10010001 2
b1 4
1)
0*
0(
#895000
b1001 0
b111111111 %
b111111111 -
b111111111 1
b111111111 5
1(
#900000
b110010001 '
b110010001 /
b110010001 2
b0 4
0(
#905000
b1010 0
b1111111111 %
b1111111111 -
b1111111111 1
b1111111111 5
1(
#910000
0(
#915000
b1101110 "
b1101110 ,
b1101110 7
b1011 0
1!
1(
#920000
0(
#925000
b1100 0
1(
#930000
0)
1*
0(
#935000
b1101 0
1(
#940000
0(
#945000
b1110 0
1(
#950000
1)
0*
0(
#955000
b1111 0
1(
#960000
0(
#965000
b0 %
b0 -
b0 1
b0 5
b0 '
b0 /
b0 2
b0 &
b0 .
b0 3
b0 6
b1010 4
1#
0$
b0 0
1(
#970000
0)
1*
0(
#975000
b1 0
0!
1(
#980000
0(
#985000
b10 0
1(
#990000
0(
#995000
b11 0
1(
#1000000
0(
#1005000
b100 0
1(
#1010000
0(
#1015000
b101 0
1(
#1020000
1)
0*
0(
#1025000
b110 0
1(
#1030000
0)
1*
0(
#1035000
b111 0
1(
#1040000
0(
#1045000
b1000 0
1(
#1050000
0(
#1055000
b1001 0
1(
#1060000
1)
0*
0(
#1065000
b1010 0
1(
#1070000
0(
#1075000
b1011 0
1(
#1080000
0(
#1085000
b1100 0
1(
#1090000
0(
#1095000
b1101 0
1(
#1100000
0(
#1105000
b1110 0
1(
#1110000
0(
#1115000
b1111 0
1(
#1120000
0(
#1125000
0#
1$
b0 0
1(
#1130000
b1001 4
0)
1*
0(
#1135000
b1 0
b1 %
b1 -
b1 1
b1 5
1(
#1140000
b1 &
b1 .
b1 3
b1 6
b1000 4
0(
#1145000
b10 0
b11 %
b11 -
b11 1
b11 5
1(
#1150000
b11 &
b11 .
b11 3
b11 6
b111 4
0(
#1155000
b11 0
b111 %
b111 -
b111 1
b111 5
1(
#1160000
b111 &
b111 .
b111 3
b111 6
b110 4
0(
#1165000
b100 0
b1111 %
b1111 -
b1111 1
b1111 5
1(
#1170000
b1111 &
b1111 .
b1111 3
b1111 6
b101 4
0(
#1175000
b101 0
b11111 %
b11111 -
b11111 1
b11111 5
1(
#1180000
b10000 '
b10000 /
b10000 2
b100 4
1)
0*
0(
#1185000
b110 0
b111111 %
b111111 -
b111111 1
b111111 5
1(
#1190000
b101111 &
b101111 .
b101111 3
b101111 6
b11 4
0)
1*
0(
#1195000
b111 0
b1111111 %
b1111111 -
b1111111 1
b1111111 5
1(
#1200000
b1101111 &
b1101111 .
b1101111 3
b1101111 6
b10 4
0(
#1205000
b1000 0
b11111111 %
b11111111 -
b11111111 1
b11111111 5
1(
#1210000
b10010000 '
b10010000 /
b10010000 2
b1 4
1)
0*
0(
#1215000
b1001 0
b111111111 %
b111111111 -
b111111111 1
b111111111 5
1(
#1220000
b110010000 '
b110010000 /
b110010000 2
b0 4
0(
#1225000
b1010 0
b1111111111 %
b1111111111 -
b1111111111 1
b1111111111 5
1(
#1230000
0)
1*
0(
#1235000
b1101111 "
b1101111 ,
b1101111 7
b1011 0
1!
1(
#1240000
0(
#1245000
b1100 0
1(
#1250000
1)
0*
0(
#1255000
b1101 0
1(
#1260000
0)
1*
0(
#1265000
b1110 0
1(
#1270000
0(
#1275000
b1111 0
1(
#1280000
0(
#1285000
b0 %
b0 -
b0 1
b0 5
b0 '
b0 /
b0 2
b0 &
b0 .
b0 3
b0 6
b1010 4
1#
0$
b0 0
1(
#1290000
0(
#1295000
b1 0
0!
1(
#1300000
1)
0*
0(
#1305000
b10 0
1(
#1310000
0(
#1315000
b11 0
1(
#1320000
0(
#1325000
b100 0
1(
#1330000
0)
1*
0(
#1335000
b101 0
1(
#1340000
1)
0*
0(
#1345000
b110 0
1(
#1350000
0(
#1355000
b111 0
1(
#1360000
0(
#1365000
b1000 0
1(
#1370000
0)
1*
0(
#1375000
b1001 0
1(
#1380000
0(
#1385000
b1010 0
1(
#1390000
1)
0*
0(
#1395000
b1011 0
1(
#1400000
0(
#1405000
b1100 0
1(
#1410000
0)
1*
0(
#1415000
b1101 0
1(
#1420000
1)
0*
0(
#1425000
b1110 0
1(
#1430000
0(
#1435000
b1111 0
1(
#1440000
0(
#1445000
0#
1$
b0 0
1(
#1450000
b1001 4
0)
1*
0(
#1455000
b1 0
b1 %
b1 -
b1 1
b1 5
1(
#1460000
b1 '
b1 /
b1 2
b1000 4
1)
0*
0(
#1465000
b10 0
b11 %
b11 -
b11 1
b11 5
1(
#1470000
b11 '
b11 /
b11 2
b111 4
0(
#1475000
b11 0
b111 %
b111 -
b111 1
b111 5
1(
#1480000
b100 &
b100 .
b100 3
b100 6
b110 4
0)
1*
0(
#1485000
b100 0
b1111 %
b1111 -
b1111 1
b1111 5
1(
#1490000
b1011 '
b1011 /
b1011 2
b101 4
1)
0*
0(
#1495000
b101 0
b11111 %
b11111 -
b11111 1
b11111 5
1(
#1500000
b10100 &
b10100 .
b10100 3
b10100 6
b100 4
0)
1*
0(
#1505000
b110 0
b111111 %
b111111 -
b111111 1
b111111 5
1(
#1510000
b110100 &
b110100 .
b110100 3
b110100 6
b11 4
0(
#1515000
b111 0
b1111111 %
b1111111 -
b1111111 1
b1111111 5
1(
#1520000
b1110100 &
b1110100 .
b1110100 3
b1110100 6
b10 4
0(
#1525000
b1000 0
b11111111 %
b11111111 -
b11111111 1
b11111111 5
1(
#1530000
b11110100 &
b11110100 .
b11110100 3
b11110100 6
b1 4
0(
#1535000
b1001 0
b111111111 %
b111111111 -
b111111111 1
b111111111 5
1(
#1540000
b111110100 &
b111110100 .
b111110100 3
b111110100 6
b0 4
0(
#1545000
b1010 0
b1111111111 %
b1111111111 -
b1111111111 1
b1111111111 5
1(
#1550000
1)
0*
0(
#1555000
b111110100 "
b111110100 ,
b111110100 7
b1011 0
1!
1(
#1560000
0(
#1565000
b1100 0
1(
#1570000
0(
#1575000
b1101 0
1(
#1580000
0)
1*
0(
#1585000
b1110 0
1(
#1590000
1)
0*
0(
#1595000
b1111 0
1(
#1600000
0(
#1605000
b0 %
b0 -
b0 1
b0 5
b0 '
b0 /
b0 2
b0 &
b0 .
b0 3
b0 6
b1010 4
1#
0$
b0 0
1(
#1610000
0)
1*
0(
#1615000
b1 0
0!
1(
#1620000
0(
#1625000
b10 0
1(
#1630000
1)
0*
0(
#1635000
b11 0
1(
#1640000
0(
#1645000
b100 0
1(
#1650000
0(
#1655000
b101 0
1(
#1660000
0)
1*
0(
#1665000
b110 0
1(
#1670000
0(
#1675000
b111 0
1(
#1680000
1)
0*
0(
#1685000
b1000 0
1(
#1690000
0(
#1695000
b1001 0
1(
#1700000
0(
#1705000
b1010 0
1(
#1710000
0)
1*
0(
#1715000
b1011 0
1(
#1720000
0(
#1725000
b1100 0
1(
#1730000
1)
0*
0(
#1735000
b1101 0
1(
#1740000
0(
#1745000
b1110 0
1(
#1750000
0(
#1755000
b1111 0
1(
#1760000
0)
1*
0(
#1765000
0#
1$
b0 0
1(
#1770000
b1001 4
1)
0*
0(
#1775000
b1 0
b1 %
b1 -
b1 1
b1 5
1(
#1780000
b1 '
b1 /
b1 2
b1000 4
0(
#1785000
b10 0
b11 %
b11 -
b11 1
b11 5
1(
#1790000
b10 &
b10 .
b10 3
b10 6
b111 4
0)
1*
0(
#1795000
b11 0
b111 %
b111 -
b111 1
b111 5
1(
#1800000
b101 '
b101 /
b101 2
b110 4
1)
0*
0(
#1805000
b100 0
b1111 %
b1111 -
b1111 1
b1111 5
1(
#1810000
b1101 '
b1101 /
b1101 2
b101 4
0(
#1815000
b101 0
b11111 %
b11111 -
b11111 1
b11111 5
1(
#1820000
b11101 '
b11101 /
b11101 2
b100 4
0(
#1825000
b110 0
b111111 %
b111111 -
b111111 1
b111111 5
1(
#1830000
b100010 &
b100010 .
b100010 3
b100010 6
b11 4
0)
1*
0(
#1835000
b111 0
b1111111 %
b1111111 -
b1111111 1
b1111111 5
1(
#1840000
b1011101 '
b1011101 /
b1011101 2
b10 4
1)
0*
0(
#1845000
b1000 0
b11111111 %
b11111111 -
b11111111 1
b11111111 5
1(
#1850000
b10100010 &
b10100010 .
b10100010 3
b10100010 6
b1 4
0)
1*
0(
#1855000
b1001 0
b111111111 %
b111111111 -
b111111111 1
b111111111 5
1(
#1860000
b110100010 &
b110100010 .
b110100010 3
b110100010 6
b0 4
0(
#1865000
b1010 0
b1111111111 %
b1111111111 -
b1111111111 1
b1111111111 5
1(
#1870000
1)
0*
0(
#1875000
b110100010 "
b110100010 ,
b110100010 7
b1011 0
1!
1(
#1880000
0(
#1885000
b1100 0
1(
#1890000
0(
#1895000
b1101 0
1(
#1900000
0(
#1905000
b1110 0
1(
#1910000
0)
1*
0(
#1915000
b1111 0
1(
#1920000
1)
0*
0(
#1925000
b0 %
b0 -
b0 1
b0 5
b0 '
b0 /
b0 2
b0 &
b0 .
b0 3
b0 6
b1010 4
1#
0$
b0 0
1(
#1930000
0(
#1935000
b1 0
0!
1(
#1940000
0(
#1945000
b10 0
1(
#1950000
0(
#1955000
b11 0
1(
#1960000
0)
1*
0(
#1965000
b100 0
1(
#1970000
0(
#1975000
b101 0
1(
#1980000
0(
#1985000
b110 0
1(
#1990000
1)
0*
0(
#1995000
b111 0
1(
